timevalue/__init__.py
timevalue/__main__.py
timevalue/annuity.py
timevalue/future.py
timevalue/present.py
timevalue/examples/annuities.md
timevalue/images/fvga.jpg
timevalue/images/sample-examples.png
timevalue/investing/__init__.py
timevalue/investing/__main__.py
timevalue/investing/annuity.py
timevalue/investing/perpetuity.py
timevalue/investing/time_value_money.py
timevalue-0.0.2.dist-info/LICENSE
timevalue-0.0.2.dist-info/METADATA
timevalue-0.0.2.dist-info/WHEEL
timevalue-0.0.2.dist-info/entry_points.txt
timevalue-0.0.2.dist-info/top_level.txt
timevalue-0.0.2.dist-info/RECORD
