Metadata-Version: 2.1
Name: timevalue
Version: 0.0.2
Summary: A simple Python package for financial valuation
Author-email: Meek Msaki <meek.dev3@gmail.com>
Maintainer-email: Meek Msaki <meek.dev3@gmail.com>
Project-URL: Homepage, https://github.com/mmsaki/timevalue
Project-URL: Bug Tracker, https://github.com/mmsaki/timevalue/issues
Keywords: analytics,investing,finance
Classifier: Development Status :: 3 - Alpha
Classifier: Intended Audience :: Developers
Classifier: Intended Audience :: Financial and Insurance Industry
Classifier: Programming Language :: Python :: 3
Classifier: Topic :: Office/Business :: Financial :: Investment
Classifier: Topic :: Software Development :: Libraries :: Python Modules
Requires-Python: >=3.7
License-File: LICENSE
